cwlprov/__init__.py
cwlprov/cwl.py
cwlprov/prov.py
cwlprov/ro.py
cwlprov/tool.py
cwlprov/utils.py
cwlprov/context/bundle.jsonld
cwlprov-0.1.1.dist-info/LICENSE.txt
cwlprov-0.1.1.dist-info/METADATA
cwlprov-0.1.1.dist-info/NOTICE
cwlprov-0.1.1.dist-info/WHEEL
cwlprov-0.1.1.dist-info/entry_points.txt
cwlprov-0.1.1.dist-info/top_level.txt
cwlprov-0.1.1.dist-info/RECORD
