Metadata-Version: 2.1
Name: cwlprov
Version: 0.1.1
Summary: cwlprov API for Python
Home-page: https://github.com/common-workflow-language/cwlprov-py
Author: Stian Soiland-Reyes
Author-email: stain@apache.org
License: Apache License, Version 2.0
Keywords: cwl prov cwlprov provenance
Platform: UNKNOWN
Classifier: Development Status :: 2 - Pre-Alpha
Classifier: Intended Audience :: Developers
Classifier: Topic :: Software Development :: Build Tools
Classifier: Programming Language :: Python :: 3
Classifier: Programming Language :: Python :: 3.6
Classifier: Topic :: Internet
Classifier: Topic :: System :: Archiving :: Packaging
Requires-Python: >=3.6, <4
Requires-Dist: prov (>=1.5.1)
Requires-Dist: bdbag (>=1.4.1)
Requires-Dist: arcp (>=0.2.0)
Requires-Dist: rdflib-jsonld (>=0.4.0)
Requires-Dist: rdflib (>=4.2.2)
